LICENSE.txt
README.md
setup.py
Topsis_102017152_Shabroz.egg-info/PKG-INFO
Topsis_102017152_Shabroz.egg-info/SOURCES.txt
Topsis_102017152_Shabroz.egg-info/dependency_links.txt
Topsis_102017152_Shabroz.egg-info/entry_points.txt
Topsis_102017152_Shabroz.egg-info/requires.txt
Topsis_102017152_Shabroz.egg-info/top_level.txt
code/102017152.py
code/__init__.py