Metadata-Version: 2.1
Name: Topsis-102017152-Shabroz
Version: 1.0.4
Summary: A package -> Calculates Topsis Score and Rank them accordingly
Author: Shabroz Kaur
Author-email: skaur2_be20@thapar.edu
License: MIT
Keywords: python package ShabrozKaur
Classifier: Programming Language :: Python
Classifier: License :: OSI Approved :: MIT License
Classifier: Operating System :: OS Independent
License-File: LICENSE.txt
